{
  "name": "pcln-design-system",
  "entries": [
    {
      "version": "5.11.0",
      "tag": "pcln-design-system_v5.11.0",
      "date": "Thu, 15 Jun 2023 18:56:18 GMT",
      "comments": {
        "patch": [
          {
            "comment": "add buttonChip state",
            "author": "Ivan Valadares <104080527+ivan-valadares@users.noreply.github.com>",
            "commit": "0a932abe2533d94886027ad1cf0198bb8200d59d"
          }
        ],
        "minor": [
          {
            "comment": "Upgrade Storybook to v7",
            "author": "Steve Dalonzo <steven.dalonzo@priceline.com>",
            "commit": "50f7b4c4b5b20c0d0854979a8478d5d2d6faf26b"
          }
        ]
      }
    },
    {
      "version": "5.10.0",
      "tag": "pcln-design-system_v5.10.0",
      "date": "Thu, 08 Jun 2023 15:26:05 GMT",
      "comments": {
        "minor": [
          {
            "comment": "Add Grid component",
            "author": "Justin Trenary <justin.trenary@priceline.com>",
            "commit": "ba327c4bd75fe3b35e76cea11beb5e93fa5c8fc1"
          }
        ],
        "patch": [
          {
            "comment": "fractional coverage regression after transpile config change",
            "author": "Steve Dalonzo <steven.dalonzo@priceline.com>",
            "commit": "2958ca59160cd9b5cd275c343fd208700f539972"
          }
        ]
      }
    },
    {
      "version": "5.9.0",
      "tag": "pcln-design-system_v5.9.0",
      "date": "Mon, 22 May 2023 13:19:55 GMT",
      "comments": {
        "minor": [
          {
            "comment": "Add optional width Prop to Button Chip",
            "author": "anjorinio <108364855+anjorinio@users.noreply.github.com>",
            "commit": "015e2754a095364f799a9e8109ebc2323b5154c8"
          }
        ],
        "patch": [
          {
            "comment": "pass props to ChipButton outline so it can have color",
            "author": "Pablo Herrera <67336461+pherrera167@users.noreply.github.com>",
            "commit": "f7e9f9213f453f003e7276363ca0e7e1e241b2a4"
          }
        ]
      }
    },
    {
      "version": "5.8.4",
      "tag": "pcln-design-system_v5.8.4",
      "date": "Tue, 02 May 2023 14:18:09 GMT",
      "comments": {
        "patch": [
          {
            "comment": "update Link with subtle, plain & white type. Also update bgcolor when button is hovered in subtle, plain & white",
            "author": "Ralston Almeida <84033935+ralston7@users.noreply.github.com>",
            "commit": "652868db1e489986e53e6808e312b2196e84d07e"
          }
        ]
      }
    },
    {
      "version": "5.8.3",
      "tag": "pcln-design-system_v5.8.3",
      "date": "Wed, 26 Apr 2023 16:50:00 GMT",
      "comments": {
        "patch": [
          {
            "comment": "Slidebox: modify to allow visibleSlides less than 1",
            "author": "ryan-hunt-priceline <62948290+ryan-hunt-priceline@users.noreply.github.com>",
            "commit": "4ca3ea28dee0135ce37c0a9b8fcff8588e8dd924"
          }
        ]
      }
    },
    {
      "version": "5.8.2",
      "tag": "pcln-design-system_v5.8.2",
      "date": "Wed, 26 Apr 2023 14:25:00 GMT",
      "comments": {
        "patch": [
          {
            "comment": "moved @styled-system/prop-types from devDependency to dependency",
            "author": "Steve Dalonzo <steven.dalonzo@priceline.com>",
            "commit": "630b1da4e822c0649d7b68786d8e714598992321"
          },
          {
            "comment": "remove propTypes from Button in favor of IButtonProps interface",
            "author": "Steve Dalonzo <steven.dalonzo@priceline.com>",
            "commit": "630b1da4e822c0649d7b68786d8e714598992321"
          }
        ]
      }
    },
    {
      "version": "5.8.1",
      "tag": "pcln-design-system_v5.8.1",
      "date": "Tue, 25 Apr 2023 21:40:50 GMT",
      "comments": {
        "patch": [
          {
            "comment": "Tweak the border variation design for Toast",
            "author": "James <62619213+pcln-james@users.noreply.github.com>",
            "commit": "b1cab98a477a4a06d720e98f09b10fceacdd5bb8"
          }
        ]
      }
    },
    {
      "version": "5.8.0",
      "tag": "pcln-design-system_v5.8.0",
      "date": "Mon, 24 Apr 2023 19:05:14 GMT",
      "comments": {
        "minor": [
          {
            "comment": "Create Toast border variation and fix overwritten styles",
            "author": "James <62619213+pcln-james@users.noreply.github.com>",
            "commit": "62b109148c3b39edfd22f6de6e10911a32ef4ff1"
          }
        ]
      }
    },
    {
      "version": "5.7.1",
      "tag": "pcln-design-system_v5.7.1",
      "date": "Wed, 12 Apr 2023 11:55:05 GMT",
      "comments": {
        "patch": [
          {
            "comment": "Use withTheme instead of useTheme in ToastProvider to restore Styled Components 4 compatibility",
            "author": "Craig Palermo <3260642+craigpalermo@users.noreply.github.com>",
            "commit": "cf9fff06cd77c28430900991dd511adc1995feb1"
          },
          {
            "comment": "Loosen styled-components peerDependency to allow v4",
            "author": "Craig Palermo <3260642+craigpalermo@users.noreply.github.com>",
            "commit": "cf9fff06cd77c28430900991dd511adc1995feb1"
          },
          {
            "comment": "Loosen styled-components peerDependency to allow v4",
            "author": "Craig Palermo <3260642+craigpalermo@users.noreply.github.com>",
            "commit": "0c189801bebf06e565d7f0f24b615b0e079ecc2a"
          }
        ]
      }
    },
    {
      "version": "5.7.0",
      "tag": "pcln-design-system_v5.7.0",
      "date": "Tue, 04 Apr 2023 20:01:00 GMT",
      "comments": {
        "minor": [
          {
            "comment": "Create Toast and ToastProvider components, add new Animations slideInleft and slideOutLeft",
            "author": "James <62619213+pcln-james@users.noreply.github.com>",
            "commit": "0193d0b584d0fc99483f018a7b64e80ac1bc6719"
          },
          {
            "comment": "add IconLeft and IconRight props to Button",
            "author": "Steve Dalonzo <steven.dalonzo@priceline.com>",
            "commit": "ef78c9732633e7a196e49e652c59ae6f9c3b3e35"
          },
          {
            "comment": "fixed peerDependency expressions",
            "author": "Steve Dalonzo <steven.dalonzo@priceline.com>",
            "commit": "ef78c9732633e7a196e49e652c59ae6f9c3b3e35"
          }
        ],
        "patch": [
          {
            "comment": "Correct text style subheading2's styles",
            "author": "Brianna Mansell <62613356+pcln-brianna@users.noreply.github.com>",
            "commit": "0c776c7877c6ae74ec39019c3d6c18ad27a667a8"
          },
          {
            "comment": "update heft component rig to remove node-sass dependence",
            "author": "Steve Dalonzo <steven.dalonzo@priceline.com>",
            "commit": "ef78c9732633e7a196e49e652c59ae6f9c3b3e35"
          },
          {
            "comment": "Upgrade Heft to 0.49.5",
            "author": "Steve Dalonzo <steven.dalonzo@priceline.com>",
            "commit": "ef78c9732633e7a196e49e652c59ae6f9c3b3e35"
          }
        ]
      }
    },
    {
      "version": "5.6.1",
      "tag": "pcln-design-system_v5.6.1",
      "date": "Wed, 22 Mar 2023 18:15:15 GMT",
      "comments": {
        "patch": [
          {
            "comment": "Fix responsive props on Label",
            "author": "Craig Palermo <3260642+craigpalermo@users.noreply.github.com>",
            "commit": "44a4ea62c28b5c10fd6b63caeaf8650aab4b27d7"
          }
        ]
      }
    },
    {
      "version": "5.6.0",
      "tag": "pcln-design-system_v5.6.0",
      "date": "Tue, 21 Mar 2023 17:01:10 GMT",
      "comments": {
        "minor": [
          {
            "comment": "Add the textStyle prop to the Label component",
            "author": "James <62619213+pcln-james@users.noreply.github.com>",
            "commit": "56bf050252eb8eeeac9e692078d9c275f2909def"
          }
        ],
        "patch": [
          {
            "comment": "Fix bug when using customBreakpoints with responsive style props",
            "author": "Craig Palermo <3260642+craigpalermo@users.noreply.github.com>",
            "commit": "bbbd8f76d93be5de4910cab7f53cd407fac5b91a"
          },
          {
            "comment": "Update FormField to use an interface instead of prop types",
            "author": "James <62619213+pcln-james@users.noreply.github.com>",
            "commit": "1832afd8f510d044e93bd376e00b7db339e356f9"
          }
        ]
      }
    },
    {
      "version": "5.5.3",
      "tag": "pcln-design-system_v5.5.3",
      "date": "Fri, 03 Mar 2023 18:23:05 GMT",
      "comments": {
        "patch": [
          {
            "comment": "Spread props for Layout to allow margin and padding overrides",
            "author": "James <62619213+pcln-james@users.noreply.github.com>",
            "commit": "821cc24c4fa47fcad064c38d4efd06bd200a3cb8"
          }
        ]
      }
    },
    {
      "version": "5.5.2",
      "tag": "pcln-design-system_v5.5.2",
      "date": "Thu, 16 Feb 2023 16:33:24 GMT",
      "comments": {
        "patch": [
          {
            "comment": "ChoiceChip text should not wrap",
            "author": "Craig Palermo <3260642+craigpalermo@users.noreply.github.com>",
            "commit": "83a42706d9e34856a378bb14fbec29e9481a04d0"
          }
        ]
      }
    },
    {
      "version": "5.5.1",
      "tag": "pcln-design-system_v5.5.1",
      "date": "Tue, 07 Feb 2023 17:29:36 GMT",
      "comments": {
        "patch": [
          {
            "comment": "Add fix for onhover color check to getLinkStylesOn",
            "author": "Brianna Mansell <62613356+pcln-brianna@users.noreply.github.com>",
            "commit": "f5ebfe04ac0d8a12b72f751a0b5ef0e20a20d0f3"
          },
          {
            "comment": "Restore fallback in getPaletteColor",
            "author": "Craig Palermo <3260642+craigpalermo@users.noreply.github.com>",
            "commit": "84012c841fdc3f0b29b5defe39d14fe33a8fd7e8"
          }
        ]
      }
    },
    {
      "version": "5.5.0",
      "tag": "pcln-design-system_v5.5.0",
      "date": "Tue, 24 Jan 2023 17:32:44 GMT",
      "comments": {
        "patch": [
          {
            "comment": "Fix bug in Checkbox when using indeterminate prop and react-hook-form",
            "author": "Craig Palermo <3260642+craigpalermo@users.noreply.github.com>",
            "commit": "8748f2527f3ac79edf86eba4c522a89578940fdf"
          }
        ],
        "minor": [
          {
            "comment": "Add util for getting link styles on a color",
            "author": "Brianna Mansell <62613356+pcln-brianna@users.noreply.github.com>",
            "commit": "31877877186559105604b09a7f2ee5415ce3f982"
          }
        ]
      }
    },
    {
      "version": "5.4.0",
      "tag": "pcln-design-system_v5.4.0",
      "date": "Tue, 17 Jan 2023 17:04:02 GMT",
      "comments": {
        "minor": [
          {
            "comment": "Copy SlideBox component from v4 branch to main (v5)",
            "author": "ryan-hunt-priceline <62948290+ryan-hunt-priceline@users.noreply.github.com>",
            "commit": "bc20a80c811304bdbf2fd0016cce9af5d4d42fb2"
          }
        ]
      }
    },
    {
      "version": "5.3.0",
      "tag": "pcln-design-system_v5.3.0",
      "date": "Tue, 13 Dec 2022 16:03:57 GMT",
      "comments": {
        "minor": [
          {
            "comment": "add Popout component",
            "author": "Justin Trenary <justin.trenary@priceline.com>",
            "commit": "5460be462112a176d8caad2a2ad9f0cf8350c395"
          }
        ]
      }
    },
    {
      "version": "5.2.0",
      "tag": "pcln-design-system_v5.2.0",
      "date": "Mon, 12 Dec 2022 20:16:28 GMT",
      "comments": {
        "minor": [
          {
            "comment": "add Animate component",
            "author": "Justin Trenary <justin.trenary@priceline.com>",
            "commit": "32ed960cde9a81d88f7d7ffdc98281543d0ba24d"
          },
          {
            "comment": "Add Button variation (input)",
            "author": "James <62619213+pcln-james@users.noreply.github.com>",
            "commit": "4f9daaa16c3f20eb790684e230c5296b63e83c5d"
          }
        ],
        "patch": [
          {
            "comment": "add border for Swatch component",
            "author": "Devin Efendy <90356592+devin-efendy-pcln@users.noreply.github.com>",
            "commit": "2caecc0a35c43ea810d6f1e4cfa30d5245932696"
          }
        ]
      }
    },
    {
      "version": "5.1.1",
      "tag": "pcln-design-system_v5.1.1",
      "date": "Wed, 23 Nov 2022 17:23:13 GMT",
      "comments": {
        "patch": [
          {
            "comment": "Visually clickable labels and improve label storybooks",
            "author": "James <62619213+pcln-james@users.noreply.github.com>",
            "commit": "fc9c7f7622ec67b1e112f83422952846074f5ecd"
          }
        ]
      }
    },
    {
      "version": "5.1.0",
      "tag": "pcln-design-system_v5.1.0",
      "date": "Wed, 09 Nov 2022 18:45:39 GMT",
      "comments": {
        "minor": [
          {
            "comment": "Add disabled state to Link and add overrides to getTextColorOn",
            "author": "James <62619213+pcln-james@users.noreply.github.com>",
            "commit": "3070d7e84b27942c0f98999fb416ed625a1f26d3"
          }
        ],
        "patch": [
          {
            "comment": "Improve TS interface for ChipContentWrapper",
            "author": "James <62619213+pcln-james@users.noreply.github.com>",
            "commit": "866e0782a5a342d74a3df0d5277c5e841f9030a1"
          }
        ]
      }
    },
    {
      "version": "5.0.0",
      "tag": "pcln-design-system_v5.0.0",
      "date": "Mon, 07 Nov 2022 16:17:23 GMT",
      "comments": {
        "major": [
          {
            "comment": "Prepare for v5 release",
            "author": "Craig Palermo <3260642+craigpalermo@users.noreply.github.com>",
            "commit": "289bd2cb648586d9ab1f691b3f75c191f07063ed"
          }
        ]
      }
    },
    {
      "version": "4.33.1",
      "tag": "pcln-design-system_v4.33.1",
      "date": "Thu, 27 Oct 2022 18:30:28 GMT",
      "comments": {
        "patch": [
          {
            "comment": "Fix serialization bug in Layout",
            "author": "Craig Palermo <3260642+craigpalermo@users.noreply.github.com>",
            "commit": "360925ec3afcbf9a2dd72411ff156d50ceb1d5a5"
          },
          {
            "comment": "Update valid border radii values for Button",
            "author": "James <62619213+pcln-james@users.noreply.github.com>",
            "commit": "f53e03e2a7247666a1b9d1ca303c62cc3df779da"
          }
        ]
      }
    },
    {
      "version": "4.33.0",
      "tag": "pcln-design-system_v4.33.0",
      "date": "Mon, 17 Oct 2022 15:52:39 GMT",
      "comments": {
        "minor": [
          {
            "comment": "Added pass through flexWrap prop for layout ",
            "author": "Brandon Soong <bsoong99@gmail.com>",
            "commit": "539d8cfbb6ba161802d09af01a88e0daf3ef734e"
          },
          {
            "comment": "create Swatch component",
            "author": "Devin Efendy <90356592+devin-efendy-pcln@users.noreply.github.com>",
            "commit": "6e763e1e99281f8eb76645ba3ec0d2109ae82e59"
          }
        ]
      }
    },
    {
      "version": "4.32.0",
      "tag": "pcln-design-system_v4.32.0",
      "date": "Wed, 05 Oct 2022 17:01:35 GMT",
      "comments": {
        "minor": [
          {
            "comment": "Added an extra large button with a height of 56px",
            "author": "Brandon Soong <bsoong99@gmail.com>",
            "commit": "ea0764def565440715caf51a3d42f42bb6fbb10b"
          },
          {
            "comment": "Added test cases, as well ",
            "author": "Brandon Soong <bsoong99@gmail.com>",
            "commit": "ea0764def565440715caf51a3d42f42bb6fbb10b"
          }
        ]
      }
    },
    {
      "version": "4.31.0",
      "tag": "pcln-design-system_v4.31.0",
      "date": "Fri, 02 Sep 2022 15:49:44 GMT",
      "comments": {
        "minor": [
          {
            "comment": "Upgrade to use @styled-system/theme-get",
            "author": "James <62619213+pcln-james@users.noreply.github.com>",
            "commit": "7c064efa9ed479207f381a876ab7d7812e0ff99e"
          }
        ]
      }
    },
    {
      "version": "4.30.1",
      "tag": "pcln-design-system_v4.30.1",
      "date": "Wed, 31 Aug 2022 14:21:32 GMT",
      "comments": {
        "patch": [
          {
            "comment": "Test change, please ignore",
            "author": "Craig Palermo <craig.palermo@priceline.com>",
            "commit": "38497bc6d6abd1b4de7efca2bd3d972ffe501da0"
          }
        ]
      }
    },
    {
      "version": "4.30.0",
      "tag": "pcln-design-system_v4.30.0",
      "date": "Wed, 31 Aug 2022 14:05:20 GMT",
      "comments": {
        "patch": [
          {
            "comment": "Fix moize perf issue determining default profile name",
            "author": "Scott Nedderman <scott.nedderman@priceline.com>",
            "commit": "398f15817f9241f4256a9dfc6baaf53b46bc81de"
          },
          {
            "comment": "Test change, please ignore",
            "author": "Craig Palermo <3260642+craigpalermo@users.noreply.github.com>",
            "commit": "3c8d13ebc58f75b65eb39ec935c5b71bbd491dfc"
          },
          {
            "comment": "Test change",
            "author": "Craig Palermo <3260642+craigpalermo@users.noreply.github.com>",
            "commit": "bdf33527d0f68cbdf33d5ccae3fdca2efceb0331"
          },
          {
            "comment": "Test change",
            "author": "Craig Palermo <3260642+craigpalermo@users.noreply.github.com>",
            "commit": "0d9fa182e732975b85ea2250f463c6eeb876a594"
          }
        ],
        "minor": [
          {
            "comment": "Add more scale values",
            "author": "Amanda Komsky <amanda.komsky@priceline.com>",
            "commit": "bd4897ad739983e4ecdb4e73e8ed4ade754e6299"
          }
        ]
      }
    },
    {
      "version": "4.29.3",
      "tag": "pcln-design-system_v4.29.3",
      "date": "Wed, 10 Aug 2022 15:39:12 GMT",
      "comments": {
        "patch": [
          {
            "comment": "Test change, please disregard",
            "author": "Craig Palermo <3260642+craigpalermo@users.noreply.github.com>",
            "commit": "73b0d07431039618b1176b664dfaeaa52e07b94d"
          }
        ]
      }
    },
    {
      "version": "4.29.2",
      "tag": "pcln-design-system_v4.29.2",
      "date": "Wed, 10 Aug 2022 14:02:31 GMT",
      "comments": {
        "patch": [
          {
            "comment": "Test change",
            "author": "Craig Palermo <craig.palermo@priceline.com>",
            "commit": "f58953f69e367fa549b65699aa33174e1fcf89f3"
          }
        ]
      }
    },
    {
      "version": "4.29.1",
      "tag": "pcln-design-system_v4.29.1",
      "date": "Mon, 08 Aug 2022 15:28:28 GMT",
      "comments": {
        "patch": [
          {
            "comment": "Forward Ref for ButtonChip",
            "author": "James <62619213+pcln-james@users.noreply.github.com>",
            "commit": "99172d0113b95ee6a85afdf44fe90b394c3b98e5"
          }
        ]
      }
    },
    {
      "version": "4.29.0",
      "tag": "pcln-design-system_v4.29.0",
      "date": "Thu, 21 Jul 2022 14:38:24 GMT",
      "comments": {
        "minor": [
          {
            "comment": "added prop for unselected checkbox color",
            "author": "anjorinio <108364855+anjorinio@users.noreply.github.com>",
            "commit": "37b6d35ab3614cc546bbff9b54d82661373d0ea8"
          }
        ]
      }
    },
    {
      "version": "4.28.0",
      "tag": "pcln-design-system_v4.28.0",
      "date": "Fri, 08 Jul 2022 13:27:48 GMT",
      "comments": {
        "minor": [
          {
            "comment": "Added an indeterminate checkbox state",
            "author": "Byro Mitchell <byron.mitchell@priceline.com>",
            "commit": "71a9320915d6ce8324cd1651665c2d456133854d"
          }
        ]
      }
    },
    {
      "version": "4.26.0",
      "tag": "pcln-design-system_v4.26.0",
      "date": "Tue, 07 Jun 2022 16:09:19 GMT",
      "comments": {
        "minor": [
          {
            "comment": "Add typography values",
            "author": "Craig Palermo <3260642+craigpalermo@users.noreply.github.com>",
            "commit": "c3c2855c9059ec6b868210db9360a628264dcd06"
          }
        ]
      }
    },
    {
      "version": "4.25.0",
      "tag": "pcln-design-system_v4.25.0",
      "date": "Thu, 02 Jun 2022 16:31:00 GMT",
      "comments": {
        "minor": [
          {
            "comment": "Add white variation to Button",
            "author": "Craig Palermo <3260642+craigpalermo@users.noreply.github.com>",
            "commit": "fc65b3e9270fbeb463df151f5af1585bd84df682"
          }
        ]
      }
    },
    {
      "version": "4.24.0",
      "tag": "pcln-design-system_v4.24.0",
      "date": "Thu, 26 May 2022 18:58:01 GMT",
      "comments": {
        "minor": [
          {
            "comment": "Add name prop to Toggle",
            "author": "Craig Palermo <3260642+craigpalermo@users.noreply.github.com>",
            "commit": "1da0a5b5e7bab9b3d23ec0c6ef335d7a6d0b7fb6"
          }
        ]
      }
    },
    {
      "version": "4.23.0",
      "tag": "pcln-design-system_v4.23.0",
      "date": "Fri, 20 May 2022 18:14:31 GMT",
      "comments": {
        "minor": [
          {
            "comment": "added sizes to input and select",
            "author": "harpreetmand <harpreetmand@gmail.com>",
            "commit": "49d858e650fc694ea6fee851787c14baeb35b0c5"
          }
        ]
      }
    },
    {
      "version": "4.22.0",
      "tag": "pcln-design-system_v4.22.0",
      "date": "Fri, 13 May 2022 16:59:33 GMT",
      "comments": {
        "minor": [
          {
            "comment": "Layout: add stretchHeight prop that will equalize heights to the tallest",
            "author": "ryan-hunt-priceline <62948290+ryan-hunt-priceline@users.noreply.github.com>",
            "commit": "89965ab3cc0d040fd4b7446e648d19bc33a7e5d9"
          }
        ]
      }
    },
    {
      "version": "4.21.0",
      "tag": "pcln-design-system_v4.21.0",
      "date": "Mon, 02 May 2022 17:34:57 GMT",
      "comments": {
        "minor": [
          {
            "comment": "add borderRadius/boxShadowSize overrides for <Button />\"",
            "author": "Bradley Rastrullo <87724279+bradras@users.noreply.github.com>",
            "commit": "325e515b8bdf75b7e651f4ff7d4226c26622fdf9"
          }
        ]
      }
    },
    {
      "version": "4.20.0",
      "tag": "pcln-design-system_v4.20.0",
      "date": "Tue, 26 Apr 2022 20:36:50 GMT",
      "comments": {
        "minor": [
          {
            "comment": "add value prop to FilterChip",
            "author": "Bradley Rastrullo <87724279+bradras@users.noreply.github.com>",
            "commit": "ca89dded6779dacd6139e2956fbe9f8ddf4aa829"
          }
        ]
      }
    },
    {
      "version": "4.19.0",
      "tag": "pcln-design-system_v4.19.0",
      "date": "Fri, 15 Apr 2022 16:52:59 GMT",
      "comments": {
        "minor": [
          {
            "comment": "Updated theme wrapper to take existing into account when merging themes",
            "author": "Daniel Giraldo <daniel.giraldo@priceline.com>",
            "commit": "d9d3aac4a64471e5cbe38b572700104a12f5c0c8"
          }
        ]
      }
    },
    {
      "version": "4.18.2",
      "tag": "pcln-design-system_v4.18.2",
      "date": "Fri, 08 Apr 2022 14:50:26 GMT",
      "comments": {
        "patch": [
          {
            "comment": "added mandatory name prop to FilterChip component",
            "author": "Sachin Gadagi <97517558+sachin-gadagi@users.noreply.github.com>",
            "commit": "70e484c668ecc0ac0ce5ed429e1b531c4ce2db0d"
          }
        ]
      }
    },
    {
      "version": "4.18.1",
      "tag": "pcln-design-system_v4.18.1",
      "date": "Mon, 04 Apr 2022 14:48:33 GMT",
      "comments": {
        "patch": [
          {
            "comment": "Add common prop support to FormField",
            "author": "James <62619213+pcln-james@users.noreply.github.com>",
            "commit": "541a5e8ca0bdfb58bfe26c5b8a342246128f9a37"
          }
        ]
      }
    },
    {
      "version": "4.18.0",
      "tag": "pcln-design-system_v4.18.0",
      "date": "Mon, 28 Mar 2022 17:54:01 GMT",
      "comments": {
        "minor": [
          {
            "comment": "Pass zIndex prop to Layout children wrappers",
            "author": "Craig Palermo <3260642+craigpalermo@users.noreply.github.com>",
            "commit": "13eda59256b8dd0d33ae83096b357eaae5db975a"
          }
        ]
      }
    },
    {
      "version": "4.17.0",
      "tag": "pcln-design-system_v4.17.0",
      "date": "Mon, 21 Mar 2022 12:59:40 GMT",
      "comments": {
        "minor": [
          {
            "comment": "Add Toggle component",
            "author": "Justin Trenary <justin.trenary@priceline.com>",
            "commit": "ad10224f131fdccff740f52f6ebbbb20d8e18430"
          }
        ]
      }
    },
    {
      "version": "4.16.3",
      "tag": "pcln-design-system_v4.16.3",
      "date": "Thu, 17 Mar 2022 16:41:16 GMT",
      "comments": {
        "patch": [
          {
            "comment": "Update borderRadii.xl to 6px for backward compatibility",
            "author": "Craig Palermo <3260642+craigpalermo@users.noreply.github.com>",
            "commit": "9a5f05bf327d29940a03bb639cc07fb4d0a1cbca"
          }
        ]
      }
    },
    {
      "version": "4.16.2",
      "tag": "pcln-design-system_v4.16.2",
      "date": "Fri, 11 Mar 2022 15:09:44 GMT",
      "comments": {
        "patch": [
          {
            "comment": "Fix bug in responsive texStyle on Text",
            "author": "Craig Palermo <3260642+craigpalermo@users.noreply.github.com>",
            "commit": "551da00c1b472cb075c7f43c272e019c19734142"
          }
        ]
      }
    },
    {
      "version": "4.16.1",
      "tag": "pcln-design-system_v4.16.1",
      "date": "Thu, 10 Mar 2022 14:31:55 GMT",
      "comments": {
        "patch": [
          {
            "comment": "Update hover state in chips label",
            "author": "Ralston Almeida <84033935+ralston7@users.noreply.github.com>",
            "commit": "605c79310fc9a34d5ff92a0a0a88af0255dad845"
          }
        ]
      }
    },
    {
      "version": "4.16.0",
      "tag": "pcln-design-system_v4.16.0",
      "date": "Mon, 07 Mar 2022 18:00:11 GMT",
      "comments": {
        "minor": [
          {
            "comment": "updates to theme.ts- added opacity, scale and updated timing functions",
            "author": "Bradley Rastrullo <87724279+bradras@users.noreply.github.com>",
            "commit": "0136dc5042d77033a2d19d4cfe133d60b761e979"
          }
        ]
      }
    },
    {
      "version": "4.15.3",
      "tag": "pcln-design-system_v4.15.3",
      "date": "Thu, 03 Mar 2022 17:06:31 GMT",
      "comments": {
        "patch": [
          {
            "comment": "change focus styling to use outline instead of box-shadow",
            "author": "Justin Trenary <justin.trenary@priceline.com>",
            "commit": "25e0bac9397d4051aa911918e4ab6798b161206d"
          }
        ]
      }
    },
    {
      "version": "4.15.2",
      "tag": "pcln-design-system_v4.15.2",
      "date": "Thu, 17 Feb 2022 14:07:41 GMT",
      "comments": {
        "patch": [
          {
            "comment": "Update focus styling for ButtonChip",
            "author": "Justin Trenary <trenaryja@gmail.com>",
            "commit": "685d9c137fe7e3b92177298dad1c10b0e7e2b41b"
          },
          {
            "comment": "Add Storybook to project, fix lint errors",
            "author": "Craig Palermo <3260642+craigpalermo@users.noreply.github.com>",
            "commit": "c9301e8e8f0f7755332f2fdb3a6192e6b7f88457"
          }
        ]
      }
    },
    {
      "version": "4.15.1",
      "tag": "pcln-design-system_v4.15.1",
      "date": "Mon, 14 Feb 2022 15:32:00 GMT",
      "comments": {
        "patch": [
          {
            "comment": "Make Layout's variation prop required",
            "author": "Craig Palermo <3260642+craigpalermo@users.noreply.github.com>",
            "commit": "10b80037faabf31a16419e2ed4705a39c7e3a8be"
          },
          {
            "comment": "Design updates to typography scale",
            "author": "Craig Palermo <3260642+craigpalermo@users.noreply.github.com>",
            "commit": "c0fafc6f52e118a27153b954cfd7a143eb40d468"
          }
        ]
      }
    },
    {
      "version": "4.15.0",
      "tag": "pcln-design-system_v4.15.0",
      "date": "Fri, 11 Feb 2022 16:43:43 GMT",
      "comments": {
        "minor": [
          {
            "comment": "Add new Motion component",
            "author": "ryan-hunt-priceline <62948290+ryan-hunt-priceline@users.noreply.github.com>",
            "commit": "0837095ad73513912c2be39199799d2e8671d26a"
          }
        ]
      }
    },
    {
      "version": "4.14.0",
      "tag": "pcln-design-system_v4.14.0",
      "date": "Mon, 31 Jan 2022 19:30:09 GMT",
      "comments": {
        "minor": [
          {
            "comment": "Create Layout component and add size prop to Container",
            "author": "Craig Palermo <3260642+craigpalermo@users.noreply.github.com>",
            "commit": "87b0c0e2d4f97c4337cf0a0989762f10db8734a5"
          }
        ]
      }
    },
    {
      "version": "4.13.1",
      "tag": "pcln-design-system_v4.13.1",
      "date": "Thu, 27 Jan 2022 14:53:43 GMT",
      "comments": {
        "patch": [
          {
            "comment": "Build with Heft",
            "author": "Craig Palermo <3260642+craigpalermo@users.noreply.github.com>",
            "commit": "b21f26fd5f90eff000e6cc125cfa0bcf3e0a6200"
          }
        ]
      }
    },
    {
      "version": "4.13.0",
      "tag": "pcln-design-system_v4.13.0",
      "date": "Fri, 14 Jan 2022 17:42:20 GMT",
      "comments": {
        "minor": [
          {
            "comment": "implement boxShadowSize and boxShadowColor props, Storybook Args improvements",
            "author": "Steve Dalonzo <steve.dalonzo+github@gmail.com>",
            "commit": "cd76e627c5888aaa3dc2fb715a206a8a4fdad28a"
          },
          {
            "comment": "Add borderRadius props to Image and BackgroundImage",
            "author": "Craig Palermo <3260642+craigpalermo@users.noreply.github.com>",
            "commit": "1a3fe28827aef2e4ad1166a7fc7ca0cf3e11c8a4"
          },
          {
            "comment": "implement borderRadius/rounded props",
            "author": "Steve Dalonzo <steve.dalonzo+github@gmail.com>",
            "commit": "57ede7dba7cb373cf2a8b51e74819331a3da1d0a"
          },
          {
            "comment": "implemented new Typography system via textStyle prop\"",
            "author": "Steve Dalonzo <steve.dalonzo+github@gmail.com>",
            "commit": "dca9a72a883a55490bc804f4b33563608cbf7a4c"
          },
          {
            "comment": "Monorepo maintenance, fixed peers",
            "author": "Steve Dalonzo <steve.dalonzo+github@gmail.com>",
            "commit": "8d8bd0bab203e5219c5d3c1596c40775ac0fb0a1"
          }
        ],
        "patch": [
          {
            "comment": "Expand color palette with new tint, tone and shade hues",
            "author": "Steve Dalonzo <steve.dalonzo+github@gmail.com>",
            "commit": "bd430e46cedd3a1c8cb0dff1591902dd745f5fed"
          },
          {
            "comment": "add missing textStyle propType to Text",
            "author": "Steve Dalonzo <steve.dalonzo+github@gmail.com>",
            "commit": "13b75238c302d15a4a49b41604f293df87b8a870"
          },
          {
            "comment": "upgrade Storybook dependencies",
            "author": "Steve Dalonzo <steve.dalonzo+github@gmail.com>",
            "commit": "5168b6242674636caee9c25601c1e7fb39df79bc"
          },
          {
            "comment": "Use new borderRadii from theme",
            "author": "Craig Palermo <3260642+craigpalermo@users.noreply.github.com>",
            "commit": "fb53a8602d0b9bd0dd9050180ec484bc03027fb8"
          }
        ]
      }
    },
    {
      "version": "4.12.1",
      "tag": "pcln-design-system_v4.12.1",
      "date": "Tue, 16 Nov 2021 15:55:41 GMT",
      "comments": {
        "patch": [
          {
            "comment": "Update dependencies with non-breaking changes",
            "author": "Craig Palermo <3260642+craigpalermo@users.noreply.github.com>",
            "commit": "81104428930aad0996558f58329db3e5be608333"
          }
        ]
      }
    },
    {
      "version": "4.12.0",
      "tag": "pcln-design-system_v4.12.0",
      "date": "Thu, 21 Oct 2021 21:09:04 GMT",
      "comments": {
        "minor": [
          {
            "comment": "applyVariations improved to support shades"
          }
        ]
      }
    },
    {
      "version": "4.11.2",
      "tag": "pcln-design-system_v4.11.2",
      "date": "Wed, 23 Jun 2021 16:13:27 GMT",
      "comments": {
        "patch": [
          {
            "comment": "Added background for focus",
            "author": "David Lu <63004067+davidhlu@users.noreply.github.com>",
            "commit": "7a07c510a6db38b2a983ca7cb7156c741b457dc9"
          }
        ]
      }
    },
    {
      "version": "4.11.1",
      "tag": "pcln-design-system_v4.11.1",
      "date": "Mon, 14 Jun 2021 18:55:11 GMT",
      "comments": {
        "patch": [
          {
            "comment": "Update props in stories",
            "author": "Craig Palermo <3260642+craigpalermo@users.noreply.github.com>",
            "commit": "1982f67de819ac1c3b0b7d5722da65eb81b1eee7"
          }
        ]
      }
    },
    {
      "version": "4.11.0",
      "tag": "pcln-design-system_v4.11.0",
      "date": "Tue, 08 Jun 2021 20:47:08 GMT",
      "comments": {
        "minor": [
          {
            "comment": "Create List Component"
          }
        ]
      }
    },
    {
      "version": "4.10.0",
      "tag": "pcln-design-system_v4.10.0",
      "date": "Wed, 26 May 2021 18:17:47 GMT",
      "comments": {
        "minor": [
          {
            "comment": "Add fontStyle and textDecoration props to Text component"
          }
        ]
      }
    },
    {
      "version": "4.9.1",
      "tag": "pcln-design-system_v4.9.1",
      "date": "Mon, 26 Apr 2021 20:36:49 GMT",
      "comments": {
        "patch": [
          {
            "comment": "Republish in order to fix a bad build"
          }
        ]
      }
    },
    {
      "version": "4.9.0",
      "tag": "pcln-design-system_v4.9.0",
      "date": "Mon, 26 Apr 2021 19:28:49 GMT",
      "comments": {
        "minor": [
          {
            "comment": "Create DotLoader component and export it and Spinner"
          },
          {
            "comment": "Create new spinner component"
          }
        ]
      }
    },
    {
      "version": "4.8.0",
      "tag": "pcln-design-system_v4.8.0",
      "date": "Thu, 15 Apr 2021 21:30:43 GMT",
      "comments": {
        "patch": [
          {
            "comment": "Export PasswordInput"
          },
          {
            "comment": "Update focus style for Chips"
          },
          {
            "comment": "Improve Text Extension components"
          },
          {
            "comment": "Upgraded to Storybook v6"
          }
        ],
        "minor": [
          {
            "comment": "PasswordInput controlled isValid props and start the progress bar empty"
          }
        ]
      }
    },
    {
      "version": "4.7.1",
      "tag": "pcln-design-system_v4.7.1",
      "date": "Tue, 23 Mar 2021 18:57:24 GMT",
      "comments": {
        "patch": [
          {
            "comment": "Fix link button variations using size prop"
          },
          {
            "comment": "Update Password Input Default Requirements"
          },
          {
            "comment": "Update pcln-icons dependency"
          }
        ]
      }
    },
    {
      "version": "4.7.0",
      "tag": "pcln-design-system_v4.7.0",
      "date": "Thu, 18 Mar 2021 18:51:55 GMT",
      "comments": {
        "patch": [
          {
            "comment": "Change exported Chip component from ChoiceChip to FilterChip",
            "author": "James <62619213+pcln-james@users.noreply.github.com>",
            "commit": "0c8c24d9352abfc3ab9d03107a57f0cdd96d4a0e"
          },
          {
            "comment": "IconField overwriting pl and pr default props fixed",
            "author": "James <62619213+pcln-james@users.noreply.github.com>",
            "commit": "04f6af9be05df3b30b8266530ee61c51f739bad6"
          }
        ],
        "minor": [
          {
            "comment": "AltText and Responsive Sizes for Avatar",
            "author": "James <62619213+pcln-james@users.noreply.github.com>",
            "commit": "046bbaac228137d5497bbb0c9b564a87aaad849c"
          },
          {
            "comment": "created a new passwordInput component",
            "author": "JonChoi16 <77304994+JonChoi16@users.noreply.github.com>",
            "commit": "47f6984a75aeba71d49f5264349dcdfeb12cf81b"
          }
        ]
      }
    },
    {
      "version": "4.6.2",
      "tag": "pcln-design-system_v4.6.2",
      "date": "Wed, 10 Mar 2021 15:09:11 GMT",
      "comments": {
        "patch": [
          {
            "comment": "Export Chip"
          }
        ]
      }
    },
    {
      "version": "4.6.1",
      "tag": "pcln-design-system_v4.6.1",
      "date": "Thu, 04 Mar 2021 20:25:55 GMT",
      "comments": {
        "patch": [
          {
            "comment": "IconField allows multiple Icon components",
            "author": "James <62619213+pcln-james@users.noreply.github.com>",
            "commit": "6d9b977aa8c91719d3ed370d276d45d6b62147b3"
          }
        ]
      }
    },
    {
      "version": "4.6.0",
      "tag": "pcln-design-system_v4.6.0",
      "date": "Tue, 02 Mar 2021 15:09:04 GMT",
      "comments": {
        "minor": [
          {
            "comment": "Created new variations of the Chip component",
            "author": "ryan-hunt-priceline <62948290+ryan-hunt-priceline@users.noreply.github.com>",
            "commit": "51d9ce82d73d875b5222fd601102148970b49a6e"
          }
        ]
      }
    },
    {
      "version": "4.5.0",
      "tag": "pcln-design-system_v4.5.0",
      "date": "Tue, 23 Feb 2021 15:06:30 GMT",
      "comments": {
        "patch": [
          {
            "comment": "Update theme blue to accessible alternative",
            "author": "Craig Palermo <3260642+craigpalermo@users.noreply.github.com>",
            "commit": "517cd819d4017a5ecaaecb00184112e1ceebe2f0"
          },
          {
            "comment": "Fix backward compatibility for props in RatingBadge",
            "author": "Craig Palermo <3260642+craigpalermo@users.noreply.github.com>",
            "commit": "05e1d7756728a8162e2d5e8f15995e62b8c18d14"
          }
        ],
        "minor": [
          {
            "comment": "Create new progress bar component",
            "author": "JonChoi16 <77304994+JonChoi16@users.noreply.github.com>",
            "commit": "761d993bd87c727d6528de38fd9ccaaf53730ff7"
          }
        ]
      }
    },
    {
      "version": "4.4.1",
      "tag": "pcln-design-system_v4.4.1",
      "date": "Wed, 17 Feb 2021 16:29:34 GMT",
      "comments": {
        "patch": [
          {
            "comment": "Fix incorrect default color of RatingBadge",
            "author": "Craig Palermo <3260642+craigpalermo@users.noreply.github.com>",
            "commit": "2e711024b8f850ef80f733abc37e42328edd3ff4"
          }
        ]
      }
    },
    {
      "version": "4.4.0",
      "tag": "pcln-design-system_v4.4.0",
      "date": "Tue, 16 Feb 2021 20:20:28 GMT",
      "comments": {
        "minor": [
          {
            "comment": "add primary, secondary, subtle, plain and warning variations to Button ",
            "author": "Gabby Bellini <63808842+gbellini911@users.noreply.github.com>",
            "commit": "6027b21e01275d558e49a1f7a0eab322cbb4009d"
          },
          {
            "comment": "Add height and spacing from styled-system to Image component",
            "author": "James <62619213+pcln-james@users.noreply.github.com>",
            "commit": "6966790a810edc44c0d71242fe5a888f703273f2"
          }
        ],
        "patch": [
          {
            "comment": "add cta check and ability to pass in a diff heading font size",
            "author": "Gabby Bellini <63808842+gbellini911@users.noreply.github.com>",
            "commit": "5171afb745789b8293340fc1ca2cb6d793557358"
          }
        ]
      }
    },
    {
      "version": "4.3.2",
      "tag": "pcln-design-system_v4.3.2",
      "date": "Wed, 03 Feb 2021 20:28:22 GMT",
      "comments": {
        "patch": [
          {
            "comment": "Update BackgroundImage height prop to accept number",
            "author": "James <62619213+pcln-james@users.noreply.github.com>",
            "commit": "b576779f081d6f019c61ad49139ab16241fee9e3"
          }
        ]
      }
    },
    {
      "version": "4.3.1",
      "tag": "pcln-design-system_v4.3.1",
      "date": "Thu, 21 Jan 2021 20:58:12 GMT",
      "comments": {
        "patch": [
          {
            "comment": "Fix ref forwarding for Input component",
            "author": "Craig Palermo <email@craigp.me>",
            "commit": "1b4c8b4656f244c30ea2c3f77db8f1815b9a3fb6"
          }
        ]
      }
    },
    {
      "version": "4.3.0",
      "tag": "pcln-design-system_v4.3.0",
      "date": "Mon, 11 Jan 2021 14:00:06 GMT",
      "comments": {
        "minor": [
          {
            "comment": "Add Shimmer component",
            "author": "Craig Palermo <3260642+craigpalermo@users.noreply.github.com>",
            "commit": "a7acba295476b1253620743671c8c7d48ddbfbd0"
          },
          {
            "comment": "Add Accessibility SkipMenu component",
            "author": "Daniel Giraldo <daniel.giraldo@priceline.com>",
            "commit": "b661954fd76583a91f1f26e8baa422c93cbd4f3f"
          },
          {
            "comment": "Add helperText prop for showing error messages in forms",
            "author": "Craig Palermo <3260642+craigpalermo@users.noreply.github.com>",
            "commit": "8ad3195e830e18511ead6cd2f1f14e614dd26025"
          },
          {
            "comment": "add a new component GenericBanner to core",
            "author": "Gabby Bellini <63808842+gbellini911@users.noreply.github.com>",
            "commit": "f96a31106e53b1f92ea0cad6bae055d497d7e4db"
          }
        ],
        "patch": [
          {
            "comment": "Fix bug when using RatingBadge with color but not bg prop",
            "author": "Craig Palermo <3260642+craigpalermo@users.noreply.github.com>",
            "commit": "366e6521107e6ccf61b2c59cfed536067a6eed55"
          },
          {
            "comment": "Resolve warnings in Storybook and remove use of deprecated styled().attrs({}) syntax",
            "author": "Craig Palermo <3260642+craigpalermo@users.noreply.github.com>",
            "commit": "b83b4e3e9b3ccae91dda80bfc87543b621631698"
          },
          {
            "comment": "Update Text Extension Display Names",
            "author": "James <62619213+pcln-james@users.noreply.github.com>",
            "commit": "7096fa92411261a21adf0c11c911d9e4a178c51e"
          },
          {
            "comment": "Change withComponent to as",
            "author": "James <62619213+pcln-james@users.noreply.github.com>",
            "commit": "48ba3457565118a7a653248804c152857cbe455d"
          }
        ]
      }
    },
    {
      "version": "4.2.1",
      "tag": "pcln-design-system_v4.2.1",
      "date": "Tue, 15 Dec 2020 01:52:10 GMT",
      "comments": {
        "patch": [
          {
            "comment": "Fix error when using Icon from pcln-icons package with IconField",
            "author": "Craig Palermo <3260642+craigpalermo@users.noreply.github.com>",
            "commit": "7287d745fcc4e43b06b89bbe3453116e8996ad4f"
          }
        ]
      }
    },
    {
      "version": "4.2.0",
      "tag": "pcln-design-system_v4.2.0",
      "date": "Fri, 11 Dec 2020 01:11:24 GMT",
      "comments": {
        "minor": [
          {
            "comment": "Add ShadowOverlay component",
            "author": "James <62619213+pcln-james@users.noreply.github.com>",
            "commit": "16d23f7d535dc6b11f933ffb40f573ad94e19798"
          }
        ]
      }
    },
    {
      "version": "4.1.2",
      "tag": "pcln-design-system_v4.1.2",
      "date": "Fri, 04 Dec 2020 20:01:32 GMT",
      "comments": {
        "patch": [
          {
            "comment": "Forward aria-label prop to Button and components that extend Button",
            "author": "Craig Palermo <email@craigp.me>",
            "commit": "76488304d488ffd757fe6fbeb54b5c1e978e8ef1"
          }
        ]
      }
    },
    {
      "version": "4.1.1",
      "tag": "pcln-design-system_v4.1.1",
      "date": "Fri, 04 Dec 2020 01:33:19 GMT",
      "comments": {
        "patch": [
          {
            "comment": "Update createTheme to overwrite MQ based on breakpoints + update applyStyles to read theme from context",
            "author": "Daniel Giraldo <daniel.giraldo@priceline.com>",
            "commit": "83e0578c04856e348c3b76ed4142ac551e4b9834"
          }
        ]
      }
    },
    {
      "version": "4.1.0",
      "tag": "pcln-design-system_v4.1.0",
      "date": "Wed, 02 Dec 2020 18:39:34 GMT",
      "comments": {
        "patch": [
          {
            "comment": "Fix prop type warning for stamp",
            "author": "James <62619213+pcln-james@users.noreply.github.com>",
            "commit": "52a66f260c2331d29e1be5f45e140bcc8184d7b9"
          }
        ],
        "minor": [
          {
            "comment": "Export applySizes",
            "author": "James <62619213+pcln-james@users.noreply.github.com>",
            "commit": "52a66f260c2331d29e1be5f45e140bcc8184d7b9"
          }
        ]
      }
    },
    {
      "version": "4.0.0",
      "tag": "pcln-design-system_v4.0.0",
      "date": "Tue, 17 Nov 2020 21:35:08 GMT",
      "comments": {
        "major": [
          {
            "comment": "React floor bump to 16.10",
            "author": "Dalonzo, Steven <Steven.Dalonzo@priceline.com>",
            "commit": "6b7189029b6d7d928ee11e4e988262cc665e3f98"
          },
          {
            "comment": "use styled-components v4 as dev and peer dependency",
            "author": "Steve Dalonzo <steve.dalonzo+github@gmail.com>",
            "commit": "0dc482906d8d580b19da1dec516a440cd43990f6"
          }
        ],
        "patch": [
          {
            "comment": "Remove usages of mapProps and getSCMigrationRef",
            "author": "Craig Palermo <3260642+craigpalermo@users.noreply.github.com>",
            "commit": "a1df40c4378a31475ea0efdf585bb3ff7382daf9"
          }
        ],
        "dependency": [
          {
            "comment": "Updating dependency \"pcln-icons\" from `4.0.0-beta.1` to `4.0.0`"
          }
        ]
      }
    },
    {
      "version": "3.7.1",
      "tag": "pcln-design-system_v3.7.1",
      "date": "Fri, 13 Nov 2020 20:04:31 GMT",
      "comments": {
        "patch": [
          {
            "comment": "Add font-weight bold back as a default style",
            "author": "James <62619213+pcln-james@users.noreply.github.com>",
            "commit": "ad001d5bc7bd677547031728edfa5c28ab509c5b"
          }
        ]
      }
    },
    {
      "version": "3.7.0",
      "tag": "pcln-design-system_v3.7.0",
      "date": "Mon, 09 Nov 2020 20:23:28 GMT",
      "comments": {
        "minor": [
          {
            "comment": "New Chip Component",
            "author": "James <62619213+pcln-james@users.noreply.github.com>",
            "commit": "fd6b9570e55a4eea5b8aff75eea59707a1305502"
          },
          {
            "comment": "allow size prop in Stamp to accept an array",
            "author": "Gabby Bellini <63808842+gbellini911@users.noreply.github.com>",
            "commit": "9da981376ffc2aad47475e46e9a4bcb916a2d334"
          }
        ],
        "patch": [
          {
            "comment": "update line height for Stamp and Badge",
            "author": "Gabby Bellini <63808842+gbellini911@users.noreply.github.com>",
            "commit": "e59e96b2103a76f0b1a8380f5ea315a2d19db37d"
          }
        ]
      }
    },
    {
      "version": "3.6.4",
      "tag": "pcln-design-system_v3.6.4",
      "date": "Fri, 30 Oct 2020 15:58:40 GMT",
      "comments": {
        "patch": [
          {
            "comment": "Remove isRequired from Checkbox's onChange",
            "author": "Benjamin Chen <benjaminlchen@gmail.com>",
            "commit": "2ad97fd91911cac9e317282612c6401d388fce5f"
          }
        ]
      }
    },
    {
      "version": "3.6.3",
      "tag": "pcln-design-system_v3.6.3",
      "date": "Fri, 23 Oct 2020 16:39:00 GMT",
      "comments": {
        "patch": [
          {
            "comment": "Manually trigger publish of new version",
            "author": "Craig Palermo <3260642+craigpalermo@users.noreply.github.com>",
            "commit": "810902108426f65ada98e0c26e96698381ced818"
          }
        ]
      }
    },
    {
      "version": "3.6.2",
      "tag": "pcln-design-system_v3.6.2",
      "date": "Fri, 23 Oct 2020 15:15:48 GMT",
      "comments": {
        "patch": [
          {
            "comment": "Remove hard coded font-weight from button / stamp"
          },
          {
            "comment": "Fix styling bug in Divider when browser zoomed-in"
          },
          {
            "comment": "Fix styling bug when using styled(Button)"
          },
          {
            "comment": "Revert change to Button that broke refs"
          }
        ]
      }
    }
  ]
}
